jsonvl/__init__.py
jsonvl/_cli/__init__.py
jsonvl/_cli/color.py
jsonvl/_cli/main.py
jsonvl/_path/__init__.py
jsonvl/_path/path_utilities.py
jsonvl/_utilities/__init__.py
jsonvl/_utilities/venum.py
jsonvl/constants/__init__.py
jsonvl/constants/builtins.py
jsonvl/constants/reserved.py
jsonvl/core/__init__.py
jsonvl/core/constraint.py
jsonvl/core/validation.py
jsonvl/core/validator.py
jsonvl/core/_array/__init__.py
jsonvl/core/_array/array_constraint_names.py
jsonvl/core/_array/array_constraints.py
jsonvl/core/_array/array_validation.py
jsonvl/core/_boolean/__init__.py
jsonvl/core/_boolean/boolean_validation.py
jsonvl/core/_null/__init__.py
jsonvl/core/_null/null_validation.py
jsonvl/core/_number/__init__.py
jsonvl/core/_number/number_constraint_names.py
jsonvl/core/_number/number_constraints.py
jsonvl/core/_number/number_validation.py
jsonvl/core/_object/__init__.py
jsonvl/core/_object/object_validation.py
jsonvl/core/_string/__init__.py
jsonvl/core/_string/string_constraint_names.py
jsonvl/core/_string/string_constraints.py
jsonvl/core/_string/string_formatting.py
jsonvl/core/_string/string_validation.py
jsonvl/errors/__init__.py
jsonvl/errors/_messages.py
jsonvl/errors/errors.py
tests/test_cli/__init__.py
tests/test_cli/test_cli.py
tests/test_cli/test_color.py
tests/test_constants/__init__.py
tests/test_constants/test_builtins.py
tests/test_errors/__init__.py
tests/test_errors/test_error_messages.py
tests/test_utilities/__init__.py
tests/test_utilities/test_venum.py
jsonvl-0.5.0.dist-info/LICENSE.txt
jsonvl-0.5.0.dist-info/METADATA
jsonvl-0.5.0.dist-info/WHEEL
jsonvl-0.5.0.dist-info/entry_points.txt
jsonvl-0.5.0.dist-info/top_level.txt
jsonvl-0.5.0.dist-info/RECORD
