Metadata-Version: 2.1
Name: jsonvl
Version: 0.5.0
Summary: JSON schema validator.
Home-page: https://github.com/gregorybchris/jsonvl
Author: Chris Gregory
Author-email: christopher.b.gregory@gmail.com
License: Apache Software License
Keywords: json,schema,validator,checker,types,typing,constraint
Platform: UNKNOWN
Classifier: Development Status :: 4 - Beta
Classifier: Intended Audience :: Developers
Classifier: License :: OSI Approved :: Apache Software License
Classifier: Operating System :: OS Independent
Classifier: Programming Language :: Python
Classifier: Programming Language :: Python :: 3.6
Classifier: Programming Language :: Python :: 3.7
Classifier: Programming Language :: Python :: 3.8
Classifier: Environment :: Console
Classifier: Natural Language :: English
Classifier: Topic :: Utilities
Provides-Extra: testing
Requires-Dist: pytest ; extra == 'testing'
Requires-Dist: pytest-cov ; extra == 'testing'
Requires-Dist: pytest-forked ; extra == 'testing'
Requires-Dist: pytest-xdist ; extra == 'testing'
Requires-Dist: pycodestyle ; extra == 'testing'
Requires-Dist: pydocstyle ; extra == 'testing'
Requires-Dist: flake8 ; extra == 'testing'
